{
  "main": {
    "id": "68b5e99451513721",
    "type": "split",
    "children": [
      {
        "id": "e91d754db468afaf",
        "type": "tabs",
        "children": [
          {
            "id": "c373b9d5d8d9f061",
            "type": "leaf",
            "state": {
              "type": "pdf",
              "state": {
                "file": "Windows Client Avancé/12. Décembre/Cours 2 - Déploiement de Windows.pdf"
              },
              "icon": "lucide-file-text",
              "title": "Cours 2 - Déploiement de Windows"
            }
          }
        ]
      }
    ],
    "direction": "vertical"
  },
  "left": {
    "id": "d32fbc6823b08ef8",
    "type": "split",
    "children": [
      {
        "id": "63b5c10ea5bde788",
        "type": "tabs",
        "children": [
          {
            "id": "6c948228a6c79cce",
            "type": "leaf",
            "state": {
              "type": "file-explorer",
              "state": {
                "sortOrder": "alphabetical"
              },
              "icon": "lucide-folder-closed",
              "title": "Files"
            }
          },
          {
            "id": "03d3764381dc1957",
            "type": "leaf",
            "state": {
              "type": "search",
              "state": {
                "query": "",
                "matchingCase": false,
                "explainSearch": false,
                "collapseAll": false,
                "extraContext": false,
                "sortOrder": "alphabetical"
              },
              "icon": "lucide-search",
              "title": "Search"
            }
          },
          {
            "id": "a9b47becbbc3a91d",
            "type": "leaf",
            "state": {
              "type": "bookmarks",
              "state": {},
              "icon": "lucide-bookmark",
              "title": "Bookmarks"
            }
          }
        ]
      }
    ],
    "direction": "horizontal",
    "width": 300
  },
  "right": {
    "id": "78f6df6de190eea1",
    "type": "split",
    "children": [
      {
        "id": "8c17c8817a610261",
        "type": "tabs",
        "children": [
          {
            "id": "c7aa612b64d29c10",
            "type": "leaf",
            "state": {
              "type": "backlink",
              "state": {
                "file": "Architecture des réseaux/11. Novembre/2024-11-04.md",
                "collapseAll": false,
                "extraContext": false,
                "sortOrder": "alphabetical",
                "showSearch": false,
                "searchQuery": "",
                "backlinkCollapsed": false,
                "unlinkedCollapsed": true
              },
              "icon": "links-coming-in",
              "title": "Backlinks for 2024-11-04"
            }
          },
          {
            "id": "7613dddd8117c9ea",
            "type": "leaf",
            "state": {
              "type": "outgoing-link",
              "state": {
                "file": "Architecture des réseaux/11. Novembre/2024-11-04.md",
                "linksCollapsed": false,
                "unlinkedCollapsed": true
              },
              "icon": "links-going-out",
              "title": "Outgoing links from 2024-11-04"
            }
          },
          {
            "id": "58e7d97bddfbc6d3",
            "type": "leaf",
            "state": {
              "type": "tag",
              "state": {
                "sortOrder": "frequency",
                "useHierarchy": true
              },
              "icon": "lucide-tags",
              "title": "Tags"
            }
          },
          {
            "id": "b669550fe33c6d7f",
            "type": "leaf",
            "state": {
              "type": "outline",
              "state": {
                "file": "Architecture des réseaux/11. Novembre/2024-11-04.md"
              },
              "icon": "lucide-list",
              "title": "Outline of 2024-11-04"
            }
          }
        ]
      }
    ],
    "direction": "horizontal",
    "width": 300,
    "collapsed": true
  },
  "left-ribbon": {
    "hiddenItems": {
      "switcher:Open quick switcher": false,
      "graph:Open graph view": false,
      "canvas:Create new canvas": false,
      "daily-notes:Open today's daily note": false,
      "templates:Insert template": false,
      "command-palette:Open command palette": false
    }
  },
  "active": "c373b9d5d8d9f061",
  "lastOpenFiles": [
    "Windows Client Avancé/12. Décembre/2024-12-04.md",
    "Windows Client Avancé/12. Décembre/Cours 2 - Déploiement de Windows.pdf",
    "Pasted image 20241204114053.png",
    "Pasted image 20241204111156.png",
    "Projet et Démarche qualité/11. Novembre/Annexes Projet v.1.1.pdf",
    "Windows Client Avancé/12. Décembre",
    "Architecture des réseaux/11. Novembre/2024-11-04.md",
    "Architecture des réseaux/11. Novembre/2024-11-05.md",
    "Projet et Démarche qualité/11. Novembre/Projet et démarche Qualité-V3.pdf",
    "Projet et Démarche qualité/11. Novembre/Projet BSRC-2 v.1.1.pdf",
    "Projet et Démarche qualité/11. Novembre/2024-11-06.md",
    "Cours/Algo/Algo 10-09-2024.md",
    "fonction.md",
    "Cours/Module A/Séance 1.md",
    "Cours/Module A/Séance 2.md",
    "Veille/Ressources web.md",
    "Cours/Algo",
    "README.md",
    "Cours/Sans titre 1",
    "Cours/Module A",
    "Veille",
    "Cours",
    "ALGO/Sommaire.md",
    "Welcome.md"
  ]
}